{"cameraMode":{"drawMode":0,"name":"Shaded","section":"Shading Mode"},"sceneLighting":false,"audioPlay":false,"sceneViewState":{"m_AlwaysRefresh":false,"showFog":true,"showSkybox":false,"showFlares":true,"showImageEffects":true,"showParticleSystems":true,"showVisualEffectGraphs":true,"m_FxEnabled":true},"in2DMode":false,"pivot":{"x":4.760632514953613,"y":1.5305216312408448,"z":-0.22801682353019715},"rotation":{"x":0.0709773451089859,"y":-0.18591715395450593,"z":0.013464678078889847,"w":0.9798880815505981},"size":6.1447577476501469,"orthographic":false}